{
  "before_frame_events": [
    { "frame_event": "can_ground_side_special" },
    { "frame_event": "can_ground_jump" },
    {
      "frame": "last",
      "buffer_animation_id": "stand",
      "buffer_animation_frame": 0
    }
  ],
  "frames": [
    {
      "sprite_sheet_id": "turn_around",
      "sprite_index": 0,
      "anchor_x": 16,
      "anchor_y": 32
    },
    {
      "sprite_sheet_id": "turn_around",
      "sprite_index": 0,
      "anchor_x": 16,
      "anchor_y": 32
    },
    {
      "sprite_sheet_id": "turn_around",
      "sprite_index": 1,
      "anchor_x": 16,
      "anchor_y": 32
    },
    {
      "sprite_sheet_id": "turn_around",
      "sprite_index": 1,
      "anchor_x": 16,
      "anchor_y": 32
    },
    {
      "sprite_sheet_id": "turn_around",
      "sprite_index": 2,
      "anchor_x": 16,
      "anchor_y": 32
    },
    {
      "sprite_sheet_id": "turn_around",
      "sprite_index": 2,
      "anchor_x": 16,
      "anchor_y": 32
    }
  ]
}